{"paths":{},"types":[],"uuids":["2dL3kvpAxJu6GJ7RdqJG5J","a8Anh32NZGRZegUtSgEj26","e8Ueib+qJEhL6mXAHdnwbi","b4P/PCArtIdIH38t6mlw8Y","71VhFCTINJM6/Ky3oX9nBT","41D7kWhyFGY7q4NDlzkazn","f0BIwQ8D5Ml7nTNQbh1YlS","e97GVMl6JHh5Ml5qEDdSGa","29FYIk+N1GYaeWH/q1NxQO"],"scenes":{"db://assets/Scene/helloworld.fire":0},"redirect":[],"deps":[],"packs":{"078a2f9d9":[8,0,5,7,6],"0caf67111":[4,1,3,2]},"name":"main","importBase":"import","nativeBase":"native","debug":false,"isZip":false,"encrypted":false,"versions":{"import":["078a2f9d9","22e11","0caf67111","8ff53"],"native":[4,"c06a9",1,"e5136",3,"83fcc",2,"90cf4"]}}